s2cache/__init__.py
s2cache/backend.py
s2cache/config.py
s2cache/conversion.py
s2cache/corpus_data.py
s2cache/filters.py
s2cache/jsonl_backend.py
s2cache/models.py
s2cache/py.typed
s2cache/semantic_scholar.py
s2cache/sql_backend.py
s2cache/sqlite_backend.py
s2cache/util.py
s2cache-0.4.1.dist-info/LICENSE.md
s2cache-0.4.1.dist-info/METADATA
s2cache-0.4.1.dist-info/WHEEL
s2cache-0.4.1.dist-info/entry_points.txt
s2cache-0.4.1.dist-info/RECORD
