Metadata-Version: 2.1
Name: s2cache
Version: 0.4.1
Summary: Unofficial Semantic Scholar API with Local Cache
Home-page: https://github.com/akshaybadola/s2cache
License: MIT
Keywords: semanticscholar,bibliography,async
Author: Akshay
Author-email: akshay.badola.cs@gmail.com
Requires-Python: >=3.8,<4.0
Classifier: Development Status :: 4 - Beta
Classifier: Intended Audience :: Science/Research
Classifier: License :: OSI Approved :: MIT License
Classifier: Natural Language :: English
Classifier: Programming Language :: Python :: 3
Classifier: Programming Language :: Python :: 3.8
Classifier: Programming Language :: Python :: 3.9
Classifier: Programming Language :: Python :: 3.10
Classifier: Programming Language :: Python :: 3.11
Classifier: Programming Language :: Python :: 3.12
Classifier: Topic :: Education
Classifier: Topic :: Scientific/Engineering
Requires-Dist: PyYAML (>=6.0.0,<7.0.0)
Requires-Dist: aiohttp (>=3.8.1,<4.0.0)
Requires-Dist: common_pyutil (>=0.9.0,<0.10.0)
Requires-Dist: mysql-connector-python (==9.3.0)
Requires-Dist: requests (>=2.31.0,<3.0.0)
